jh_pbar/__init__.py
jh_pbar/jh_pbar.py
jh_pbar/test.py
jh_pbar-1.2.dist-info/METADATA
jh_pbar-1.2.dist-info/WHEEL
jh_pbar-1.2.dist-info/top_level.txt
jh_pbar-1.2.dist-info/RECORD
